{
  "project_info": {
    "project_number": "673633567164",
    "project_id": "android-app-c9212",
    "storage_bucket": "android-app-c9212.firebasestorage.app"
  },
  "client": [
    {
      "client_info": {
        "mobilesdk_app_id": "1:673633567164:android:27a1532ec462a462f2abb9",
        "android_client_info": {
  "package_name": "io.metamask"
      }

      },
      "oauth_client": [],
      "api_key": [
        {
          "current_key": "AIzaSyAhbp3j_vajUnnWY3YjKd-s4wyDICdn_fE"
        }
      ],
      "services": {
        "appinvite_service": {
          "other_platform_oauth_client": []
        }
      }
    },
    {
      "client_info": {
        "mobilesdk_app_id": "1:673633567164:android:d1347c0ef358d7fbf2abb9",
        "android_client_info": {
          "package_name": "io.metamask"
        }
      },
      "oauth_client": [],
      "api_key": [
        {
          "current_key": "AIzaSyAhbp3j_vajUnnWY3YjKd-s4wyDICdn_fE"
        }
      ],
      "services": {
        "appinvite_service": {
          "other_platform_oauth_client": []
        }
      }
    },
    {
      "client_info": {
        "mobilesdk_app_id": "1:673633567164:android:e1b62f81dc37ad27f2abb9",
        "android_client_info": {
          "package_name": "io.metamask.flask"
        }
      },
      "oauth_client": [],
      "api_key": [
        {
          "current_key": "AIzaSyAhbp3j_vajUnnWY3YjKd-s4wyDICdn_fE"
        }
      ],
      "services": {
        "appinvite_service": {
          "other_platform_oauth_client": []
        }
      }
    }
  ],
  "configuration_version": "1"
}